pyterse.cpython-39-darwin.so
pyterse-0.1.7.dist-info/RECORD
pyterse-0.1.7.dist-info/WHEEL
pyterse-0.1.7.dist-info/METADATA
