Metadata-Version: 2.2
Name: pyterse
Version: 0.1.7
Summary: A Python interface for the TRPX compression algorithm
Author-Email: Senik Matinyan <matinyan.senik@gmail.com>
License: MIT License
Classifier: Programming Language :: Python :: 3
Classifier: Programming Language :: Python :: 3.9
Classifier: Programming Language :: Python :: 3.10
Classifier: Programming Language :: Python :: 3.11
Classifier: Programming Language :: Python :: 3.12
Classifier: Programming Language :: Python :: 3.13
Classifier: License :: OSI Approved :: MIT License
Classifier: Operating System :: OS Independent
Requires-Python: >=3.9
